djadmin/__init__.py
djadmin/apps.py
djadmin/conf.py
djadmin/dataclasses.py
djadmin/decorators.py
djadmin/forms.py
djadmin/inlines.py
djadmin/layout.py
djadmin/options.py
djadmin/sites.py
djadmin/testing.py
djadmin/views.py
djadmin/actions/__init__.py
djadmin/actions/base.py
djadmin/actions/dashboard.py
djadmin/actions/view_mixins.py
djadmin/factories/__init__.py
djadmin/factories/base.py
djadmin/management/__init__.py
djadmin/management/commands/__init__.py
djadmin/management/commands/djadmin_inspect.py
djadmin/management/commands/djadmin_list_apps.py
djadmin/plugins/__init__.py
djadmin/plugins/modifiers.py
djadmin/plugins/contrib_auth/__init__.py
djadmin/plugins/contrib_auth/actions.py
djadmin/plugins/contrib_auth/apps.py
djadmin/plugins/contrib_auth/djadmin.py
djadmin/plugins/contrib_auth/djadmin_hooks.py
djadmin/plugins/contrib_auth/forms.py
djadmin/plugins/core/__init__.py
djadmin/plugins/core/actions.py
djadmin/plugins/core/djadmin_hooks.py
djadmin/plugins/core/mixins.py
djadmin/plugins/core/utils.py
djadmin/plugins/permissions/__init__.py
djadmin/plugins/permissions/apps.py
djadmin/plugins/permissions/djadmin_hooks.py
djadmin/plugins/permissions/mixins.py
djadmin/plugins/permissions/operators.py
djadmin/plugins/permissions/permissions.py
djadmin/plugins/theme/__init__.py
djadmin/plugins/theme/apps.py
djadmin/plugins/theme/djadmin_hooks.py
djadmin/plugins/theme/static/djadmin/theme/css/theme.css
djadmin/plugins/theme/static/djadmin/theme/js/admin.js
djadmin/plugins/theme/templates/djadmin/_navigation.html
djadmin/plugins/theme/templates/registration/logged_out.html
djadmin/plugins/theme/templates/registration/login.html
djadmin/templates/djadmin/_navigation.html
djadmin/templates/djadmin/admin_base.html
djadmin/templates/djadmin/app_dashboard.html
djadmin/templates/djadmin/base_action.html
djadmin/templates/djadmin/project_dashboard.html
djadmin/templates/djadmin/actions/_detail_item.html
djadmin/templates/djadmin/actions/add.html
django_admin_deux-0.1.5.dist-info/METADATA
django_admin_deux-0.1.5.dist-info/WHEEL
django_admin_deux-0.1.5.dist-info/top_level.txt
django_admin_deux-0.1.5.dist-info/RECORD
