Metadata-Version: 2.4
Name: django-admin-deux
Version: 0.1.5
Summary: A modern, extensible replacement for Django admin
Author-email: Emma Delescolle <dev@levit.be>
Project-URL: Repository, https://codeberg.org/emmaDelescolle/django-admin-deux
Project-URL: Documentation, https://django-admin-deux.readthedocs.io/
Project-URL: Homepage, https://django-admin-deux.readthedocs.io/
Classifier: Development Status :: 3 - Alpha
Classifier: Framework :: Django
Classifier: Framework :: Django :: 5.2
Classifier: Framework :: Django :: 6.0
Classifier: Programming Language :: Python :: 3.11
Classifier: Programming Language :: Python :: 3.12
Classifier: Programming Language :: Python :: 3.13
Classifier: Programming Language :: Python :: 3.14
Requires-Python: >=3.11
Requires-Dist: Django>=5.2
Requires-Dist: djp>=0.1.0
Provides-Extra: full
Requires-Dist: djadmin-formset>=0.1.0; extra == "full"
Requires-Dist: djadmin-filters>=0.1.0; extra == "full"
Requires-Dist: djadmin-classy-doc>=0.1.0; extra == "full"
Provides-Extra: dev
Requires-Dist: pytest>=7.0; extra == "dev"
Requires-Dist: pytest-django>=4.0; extra == "dev"
Requires-Dist: pytest-cov>=4.0; extra == "dev"
Requires-Dist: pytest-factoryboy>=2.6.0; extra == "dev"
Requires-Dist: factory-boy>=3.3.0; extra == "dev"
Requires-Dist: faker>=22.0.0; extra == "dev"
Requires-Dist: ruff>=0.8.0; extra == "dev"
Requires-Dist: djlint>=1.34.0; extra == "dev"
Requires-Dist: pre-commit>=3.0.0; extra == "dev"
Provides-Extra: docs
Requires-Dist: mkdocs-material>=9.0; extra == "docs"
Requires-Dist: mkdocstrings[python]>=0.24.0; extra == "docs"
